animeface/_nvxs.pypy37-pp73-x86-linux-gnu.so
animeface/__init__.py
animeface/_nvxs.py
animeface-2.0.3.dist-info/top_level.txt
animeface-2.0.3.dist-info/RECORD
animeface-2.0.3.dist-info/LICENSE
animeface-2.0.3.dist-info/METADATA
animeface-2.0.3.dist-info/WHEEL
animeface.libs/libnvxs-ad191bf7.so.0.0.0
